Metadata-Version: 2.1
Name: docassemble.microsoftgraph
Version: 0.0.6
Summary: Docassemble interface for Microsoft Graph API.
Home-page: https://docassemble.org
Author: Quinten Steenhuis
Author-email: admin@admin.com
License: The MIT License (MIT)
Platform: UNKNOWN
